{
  "function": {
    "avantcreativedev927c2e93CustomMessage": {
      "build": true,
      "providerPlugin": "awscloudformation",
      "service": "Lambda"
    }
  },
  "auth": {
    "avantcreativedev927c2e93": {
      "service": "Cognito",
      "providerPlugin": "awscloudformation",
      "dependsOn": [
        {
          "category": "function",
          "resourceName": "avantcreativedev927c2e93CustomMessage",
          "triggerProvider": "Cognito",
          "attributes": [
            "Arn",
            "Name"
          ]
        }
      ]
    }
  },
  "api": {
    "avantcreativedevapi": {
      "service": "AppSync",
      "providerPlugin": "awscloudformation",
      "output": {
        "authConfig": {
          "defaultAuthentication": {
            "authenticationType": "API_KEY",
            "apiKeyConfig": {
              "apiKeyExpirationDays": 7,
              "description": "Avant Creative API Key"
            }
          },
          "additionalAuthenticationProviders": [
            {
              "authenticationType": "AMAZON_COGNITO_USER_POOLS",
              "userPoolConfig": {
                "userPoolId": "authavantcreativedev927c2e93"
              }
            }
          ]
        }
      }
    }
  }
}